launch_app.py
ai_app/__init__.py
ai_app/admin.py
ai_app/ai_utils.py
ai_app/core.py
ai_app/frontend.py
ai_app/pii.py
ai_app/rag.py
ai_app/sql.py
ai_app/utils.py
ai_app/app/__init__.py
ai_app/app/gradio.py
ai_app/app/middleware.py
ai_app/apps/__init__.py
ai_app/apps/governance_agent/__init__.py
ai_app/apps/governance_agent/backend.py
ai_app/apps/governance_agent/frontend.py
ai_app/apps/jira_manual_tests/__init__.py
ai_app/apps/jira_manual_tests/backend.py
ai_app/apps/jira_manual_tests/frontend.py
ai_app/apps/jira_service_desk/__init__.py
ai_app/apps/jira_service_desk/agent_graph.py
ai_app/apps/jira_service_desk/backend.py
ai_app/apps/jira_service_desk/data.py
ai_app/apps/jira_service_desk/evaluation.py
ai_app/apps/jira_service_desk/frontend.py
ai_app/apps/jira_service_desk/preparation.py
ai_app/apps/jira_service_desk/tools.py
ai_app/apps/merge_request_review/__init__.py
ai_app/apps/merge_request_review/backend.py
ai_app/apps/merge_request_review/frontend.py
ai_app/apps/presentation_review/__init__.py
ai_app/apps/presentation_review/backend.py
ai_app/apps/presentation_review/frontend.py
ai_app/apps/software_requirements_specification/__init__.py
ai_app/apps/software_requirements_specification/backend.py
ai_app/apps/software_requirements_specification/frontend.py
ai_app/apps/sql_agent/__init__.py
ai_app/apps/sql_agent/backend.py
ai_app/apps/sql_agent/frontend.py
ai_app/apps/voice_assistant/__init__.py
ai_app/apps/voice_assistant/backend.py
ai_app/apps/voice_assistant/frontend.py
ai_app/apps/voice_assistant/local_backend.py
ai_app/auth/__init__.py
ai_app/auth/utils.py
ai_app/config/__init__.py
ai_app/config/ai.py
ai_app/config/apps.py
ai_app/config/external.py
ai_app/config/middleware.py
ai_app/config/sanitation.py
ai_app/config/secrets.py
ai_app/config/sql.py
ai_app/external/__init__.py
ai_app/external/atlassian.py
ai_app/external/consul.py
ai_app/external/gitlab.py
ai_app/external/google.py
ai_app/external/openai.py
ai_app/external/providers.py
ai_app-0.1.5.dist-info/METADATA
ai_app-0.1.5.dist-info/WHEEL
ai_app-0.1.5.dist-info/entry_points.txt
ai_app-0.1.5.dist-info/top_level.txt
ai_app-0.1.5.dist-info/RECORD
