Metadata-Version: 2.4
Name: ai_app
Version: 0.1.5
Summary: AI web app for internal corporate use
Requires-Python: <3.13,>=3.12
Requires-Dist: atlassian-python-api>=3.41.19
Requires-Dist: authlib>=1.5.2
Requires-Dist: bidict>=0.23.1
Requires-Dist: bir-mcp==0.3.13
Requires-Dist: cachetools>=5.5.2
Requires-Dist: gradio>=5.18.0
Requires-Dist: httpx>=0.28.1
Requires-Dist: itsdangerous>=2.2.0
Requires-Dist: langchain>=0.3.19
Requires-Dist: langchain-community>=0.3.18
Requires-Dist: langchain-google-genai>=2.0.11
Requires-Dist: langchain-openai>=0.3.7
Requires-Dist: langchain-postgres>=0.0.15
Requires-Dist: langgraph>=0.3.5
Requires-Dist: langsmith>=0.3.11
Requires-Dist: limits>=5.2.0
Requires-Dist: logfire[fastapi,httpx,sqlalchemy,system-metrics]>=3.17.0
Requires-Dist: pgvector>=0.3.6
Requires-Dist: polars>=1.23.0
Requires-Dist: presidio-analyzer>=2.2.358
Requires-Dist: presidio-anonymizer>=2.2.358
Requires-Dist: psycopg[binary,pool]>=3.2.9
Requires-Dist: py-consul>=1.5.4
Requires-Dist: python-gitlab[graphql]>=5.6.0
Requires-Dist: sqlmodel>=0.0.24
Requires-Dist: alembic>=1.16.2
Requires-Dist: google-api-python-client>=2.164.0
Requires-Dist: google-auth-oauthlib>=1.2.1
Requires-Dist: google-cloud-iam>=2.18.1
Requires-Dist: langchain-anthropic>=0.3.16
Requires-Dist: typer>=0.16.0
Requires-Dist: pip>=25.1.1
Requires-Dist: sqlalchemy[asyncio]>=2.0.41
Requires-Dist: lxml>=6.0.0
Provides-Extra: extra
Requires-Dist: langchain-chroma>=0.2.2; extra == "extra"
Requires-Dist: langchain-huggingface>=0.1.2; extra == "extra"
Requires-Dist: scipy>=1.16.0; extra == "extra"
Requires-Dist: zyphra>=0.1.4; extra == "extra"
Requires-Dist: llama-index>=0.12.42; extra == "extra"
Requires-Dist: llama-index-vector-stores-postgres>=0.5.3; extra == "extra"
Requires-Dist: oracledb>=3.1.1; extra == "extra"
